plone.recipe.sublimetext-1.1.2-py2.7-nspkg.pth
plone/recipe/sublimetext/README.rst
plone/recipe/sublimetext/__init__.py
plone/recipe/sublimetext/recipes.py
plone/recipe/sublimetext/template.json
plone/recipe/sublimetext/tests/__init__.py
plone/recipe/sublimetext/tests/recipe.rst
plone/recipe/sublimetext/tests/test_docs.py
plone/recipe/sublimetext/tests/test_recipes.py
plone/recipe/sublimetext/tests/Products/SublimeTestProduct/__init__.py
plone/recipe/sublimetext/tests/Products/SublimeTestProduct/production.txt
plone/recipe/sublimetext/tests/develop/sublimtexttest_pkg1/.gitignore
plone/recipe/sublimetext/tests/develop/sublimtexttest_pkg1/LICENSE
plone/recipe/sublimetext/tests/develop/sublimtexttest_pkg1/MANIFEST.in
plone/recipe/sublimetext/tests/develop/sublimtexttest_pkg1/README.rst
plone/recipe/sublimetext/tests/develop/sublimtexttest_pkg1/setup.py
plone/recipe/sublimetext/tests/develop/sublimtexttest_pkg1/sublimtexttest_pkg1/__init__.py
plone/recipe/sublimetext/tests/develop/sublimtexttest_pkg1/sublimtexttest_pkg1/sublimtexttest_pkg1.py
plone.recipe.sublimetext-1.1.2.dist-info/DESCRIPTION.rst
plone.recipe.sublimetext-1.1.2.dist-info/METADATA
plone.recipe.sublimetext-1.1.2.dist-info/RECORD
plone.recipe.sublimetext-1.1.2.dist-info/WHEEL
plone.recipe.sublimetext-1.1.2.dist-info/entry_points.txt
plone.recipe.sublimetext-1.1.2.dist-info/metadata.json
plone.recipe.sublimetext-1.1.2.dist-info/namespace_packages.txt
plone.recipe.sublimetext-1.1.2.dist-info/top_level.txt
