Metadata-Version: 2.0
Name: plone.recipe.sublimetext
Version: 1.1.2
Summary: SublimeText configuration for buildout-based Python projects
Home-page: https://github.com/nazrulworld/plone.recipe.sublimetext
Author: Md Nazrul Islam
Author-email: connect2nazrul@gmail.com
License: GPL version 2
Keywords: python buildout plone sublime-text jedi sublimelinter buildout-recipe anaconda
Platform: UNKNOWN
Classifier: Environment :: Web Environment
Classifier: Development Status :: 5 - Production/Stable
Classifier: Framework :: Plone
Classifier: Framework :: Plone :: 4.3
Classifier: Framework :: Plone :: 5.0
Classifier: Framework :: Plone :: 5.1
Classifier: Programming Language :: Python
Classifier: Programming Language :: Python :: 2.7
Classifier: Programming Language :: Python :: 3.4
Classifier: Programming Language :: Python :: 3.5
Classifier: Programming Language :: Python :: 3.6
Classifier: Operating System :: OS Independent
Classifier: Topic :: Software Development :: Build Tools
Classifier: License :: OSI Approved :: GNU General Public License v2 (GPLv2)
Requires-Dist: setuptools
Requires-Dist: zc.buildout
Requires-Dist: zc.recipe.egg
Provides-Extra: test
Requires-Dist: zope.testing; extra == 'test'
Requires-Dist: zc.buildout[test]; extra == 'test'
Requires-Dist: zc.recipe.egg; extra == 'test'
